[
  {
    "id": "e49603ec-e31a-4c8a-8091-3fac5161a468",
    "title": "新笔记",
    "content": "",
    "category": "4",
    "tags": [],
    "user": "anonymous",
    "createdAt": 1775102089313,
    "updatedAt": 1775102420414
  },
  {
    "id": "c6e8de54-854e-4160-8021-78e3db5bba1b",
    "title": "新笔记",
    "content": "",
    "category": "4",
    "tags": [],
    "user": "anonymous",
    "createdAt": 1775101797537,
    "updatedAt": 1775102420272
  },
  {
    "id": "0c28e923-918a-49b7-bfdb-e0b85a26867e",
    "title": "新笔记",
    "content": "",
    "category": "4",
    "tags": [],
    "user": "anonymous",
    "createdAt": 1775100861595,
    "updatedAt": 1775102419938
  },
  {
    "id": "1fbd7e7b-b793-450c-be8a-7d1abae379a1",
    "title": "新笔记",
    "content": "",
    "category": "4",
    "tags": [],
    "user": "anonymous",
    "createdAt": 1775100496405,
    "updatedAt": 1775102419847
  },
  {
    "id": "1d173530-4b15-43ad-beaa-7e2fcad6cf28",
    "title": "新笔记",
    "content": "hhhh\n",
    "category": "4",
    "tags": [],
    "user": "anonymous",
    "createdAt": 1775099773879,
    "updatedAt": 1775102419698
  },
  {
    "id": "2b2f5223-5092-48cf-abc8-91221bd41a88",
    "title": "新笔记",
    "content": "hhh\n",
    "category": "4",
    "tags": [],
    "user": "anonymous",
    "createdAt": 1775099711504,
    "updatedAt": 1775102418966
  },
  {
    "id": "b523d5ee-9bad-4d46-9862-f2bd00559d75",
    "title": "新笔记",
    "content": "hhh\n",
    "category": "4",
    "tags": [],
    "user": "anonymous",
    "createdAt": 1775099081290,
    "updatedAt": 1775102418621
  },
  {
    "id": "3098e02f-31cb-4cb7-a6a8-590293daac8b",
    "title": "新笔记",
    "content": "shhshb s\n",
    "category": "4",
    "tags": [],
    "createdAt": 1775035556306,
    "updatedAt": 1775102541688
  },
  {
    "id": "c501ea8f-8d2c-4fe5-9ef6-6d57a974b455",
    "title": "新笔记",
    "content": "hhh![微信图片_20260401161608_269_6.png](/api/attachments/c501ea8f-8d2c-4fe5-9ef6-6d57a974b455/1775034892546-微信图片_20260401161608_269_6.png)\n",
    "category": "4",
    "tags": [],
    "createdAt": 1775031453553,
    "updatedAt": 1775034896930
  }
]